Metadata-Version: 2.1
Name: bnnumerizer
Version: 0.0.1
Summary: Bangla Number text to String Converter
Home-page: https://github.com/banglakit/number-to-bengali-word
Author: Aniruddha Adhikary,Mahir Labib Chowdhury
Author-email: 
License: MIT
Keywords: bangla,number,word numerizer
Platform: UNKNOWN
Classifier: Development Status :: 3 - Alpha
Classifier: Intended Audience :: Education
Classifier: Operating System :: OS Independent
Classifier: License :: OSI Approved :: MIT License
Classifier: Programming Language :: Python :: 3
License-File: LICENSE
